[
  {
    "type": "function",
    "name": "addOwner",
    "inputs": [
      { "name": "account", "type": "address", "internalType": "address" },
      { "name": "owner", "type": "address", "internalType": "address" }
    ],
    "outputs": [],
    "stateMutability": "nonpayable"
  },
  {
    "type": "function",
    "name": "getOwners",
    "inputs": [
      { "name": "account", "type": "address", "internalType": "address" }
    ],
    "outputs": [
      { "name": "", "type": "address[]", "internalType": "address[]" }
    ],
    "stateMutability": "view"
  },
  {
    "type": "function",
    "name": "isOwner",
    "inputs": [
      { "name": "account", "type": "address", "internalType": "address" },
      { "name": "owner", "type": "address", "internalType": "address" }
    ],
    "outputs": [{ "name": "", "type": "bool", "internalType": "bool" }],
    "stateMutability": "view"
  },
  {
    "type": "function",
    "name": "removeOwner",
    "inputs": [
      { "name": "account", "type": "address", "internalType": "address" },
      { "name": "prevOwner", "type": "address", "internalType": "address" },
      { "name": "owner", "type": "address", "internalType": "address" }
    ],
    "outputs": [],
    "stateMutability": "nonpayable"
  },
  {
    "type": "function",
    "name": "swapOwner",
    "inputs": [
      { "name": "account", "type": "address", "internalType": "address" },
      { "name": "prevOwner", "type": "address", "internalType": "address" },
      { "name": "oldOwner", "type": "address", "internalType": "address" },
      { "name": "newOwner", "type": "address", "internalType": "address" }
    ],
    "outputs": [],
    "stateMutability": "nonpayable"
  },
  {
    "type": "event",
    "name": "AddedOwner",
    "inputs": [
      {
        "name": "owner",
        "type": "address",
        "indexed": true,
        "internalType": "address"
      }
    ],
    "anonymous": false
  },
  {
    "type": "event",
    "name": "RemovedOwner",
    "inputs": [
      {
        "name": "owner",
        "type": "address",
        "indexed": true,
        "internalType": "address"
      }
    ],
    "anonymous": false
  },
  { "type": "error", "name": "DuplicateOwner", "inputs": [] },
  { "type": "error", "name": "InvalidOwner", "inputs": [] },
  { "type": "error", "name": "LastOwnerRemovalNotAllowed", "inputs": [] },
  { "type": "error", "name": "OwnerMismatch", "inputs": [] }
]
